vnag/__init__.py
vnag/__main__.py
vnag/agent.py
vnag/constant.py
vnag/embedder.py
vnag/engine.py
vnag/gateway.py
vnag/local.py
vnag/mcp.py
vnag/object.py
vnag/py.typed
vnag/segmenter.py
vnag/tracer.py
vnag/utility.py
vnag/vector.py
vnag/embedders/__init__.py
vnag/embedders/dashscope_embedder.py
vnag/embedders/openai_embedder.py
vnag/embedders/sentence_embedder.py
vnag/gateways/__init__.py
vnag/gateways/anthropic_gateway.py
vnag/gateways/bailian_gateway.py
vnag/gateways/dashscope_gateway.py
vnag/gateways/deepseek_gateway.py
vnag/gateways/litellm_gateway.py
vnag/gateways/minimax_gateway.py
vnag/gateways/openai_gateway.py
vnag/gateways/openrouter_gateway.py
vnag/segmenters/__init__.py
vnag/segmenters/cpp_segmenter.py
vnag/segmenters/markdown_segmenter.py
vnag/segmenters/python_segmenter.py
vnag/segmenters/simple_segmenter.py
vnag/tools/__init__.py
vnag/tools/code_tools.py
vnag/tools/datetime_tools.py
vnag/tools/file_tools.py
vnag/tools/network_tools.py
vnag/tools/search_tools.py
vnag/tools/web_tools.py
vnag/ui/__init__.py
vnag/ui/factory.py
vnag/ui/logo.ico
vnag/ui/qt.py
vnag/ui/setting.py
vnag/ui/widget.py
vnag/ui/window.py
vnag/ui/worker.py
vnag/ui/resources/chat.html
vnag/ui/resources/highlight.min.js
vnag/ui/resources/markdown-it.min.js
vnag/ui/resources/monokai-sublime.min.css
vnag/ui/resources/style.css
vnag/vectors/__init__.py
vnag/vectors/chromadb_vector.py
vnag/vectors/qdrant_vector.py
vnag-0.7.0.dist-info/METADATA
vnag-0.7.0.dist-info/WHEEL
vnag-0.7.0.dist-info/licenses/LICENSE
vnag-0.7.0.dist-info/RECORD
