Metadata-Version: 2.4
Name: vnag
Version: 0.7.0
Summary: VeighNa agent framework.
Author-email: Xiaoyou Chen <xiaoyou.chen@mail.vnpy.com>
License: MIT
License-File: LICENSE
Keywords: agent,ai
Classifier: Development Status :: 5 - Production/Stable
Classifier: License :: OSI Approved :: MIT License
Classifier: Natural Language :: Chinese (Simplified)
Classifier: Operating System :: OS Independent
Classifier: Programming Language :: Python :: 3
Classifier: Programming Language :: Python :: 3.10
Classifier: Programming Language :: Python :: 3.11
Classifier: Programming Language :: Python :: 3.12
Classifier: Programming Language :: Python :: 3.13
Classifier: Programming Language :: Python :: Implementation :: CPython
Classifier: Topic :: Office/Business :: Financial :: Investment
Requires-Python: >=3.10
Requires-Dist: anthropic
Requires-Dist: chardet
Requires-Dist: dashscope
Requires-Dist: fastmcp
Requires-Dist: loguru
Requires-Dist: openai
Requires-Dist: pydantic
Requires-Dist: pyside6
Requires-Dist: pyside6-addons
Requires-Dist: qdarkstyle
Requires-Dist: requests
Provides-Extra: rag
Requires-Dist: chromadb; extra == 'rag'
Requires-Dist: libclang; extra == 'rag'
Requires-Dist: markdown-it-py; extra == 'rag'
Requires-Dist: numpy; extra == 'rag'
Requires-Dist: qdrant-client; extra == 'rag'
Requires-Dist: sentence-transformers; extra == 'rag'
